moondream/__init__.py
moondream/torch/__init__.py
moondream/torch/inference.py
moondream/torch/layers.py
moondream/torch/rope.py
moondream/torch/text.py
moondream/torch/vision.py
moondream/torch/weights.py
moondream-1.0.3.dist-info/LICENSE
moondream-1.0.3.dist-info/METADATA
moondream-1.0.3.dist-info/WHEEL
moondream-1.0.3.dist-info/entry_points.txt
moondream-1.0.3.dist-info/top_level.txt
moondream-1.0.3.dist-info/RECORD
