Metadata-Version: 2.1
Name: moondream
Version: 1.0.3
Summary: A package for image-based question answering using Moondream
Home-page: https://github.com/1997MarsRover/moondream
Author: 1997marsrover
Author-email: antonygithinji11156@gmail.com
Project-URL: Bug Tracker, https://github.com/1997MarsRover/moondream/issues
Project-URL: Documentation, https://github.com/1997MarsRover/moondream#readme
Project-URL: Source Code, https://github.com/1997MarsRover/moondream
Classifier: Development Status :: 5 - Production/Stable
Classifier: Intended Audience :: Developers
Classifier: Intended Audience :: Science/Research
Classifier: License :: OSI Approved :: MIT License
Classifier: Programming Language :: Python :: 3
Classifier: Programming Language :: Python :: 3.8
Classifier: Programming Language :: Python :: 3.9
Classifier: Programming Language :: Python :: 3.10
Requires-Python: >=3.7
License-File: LICENSE
Requires-Dist: torch
Requires-Dist: Pillow
Requires-Dist: transformers
